LICENSE
MANIFEST.in
README.rst
setup.py
version.py
vagrant/__init__.py
vagrant/core.py
vagrant_environment.egg-info/PKG-INFO
vagrant_environment.egg-info/SOURCES.txt
vagrant_environment.egg-info/dependency_links.txt
vagrant_environment.egg-info/not-zip-safe
vagrant_environment.egg-info/top_level.txt