Metadata-Version: 1.1
Name: vagrant-environment
Version: 0.1.0
Summary: Partial Python wrapper of the `vagrant` command
Home-page: https://github.com/carletes/vagrant-environment
Author: Carlos Valiente
Author-email: carlos@pepelabs.net
License: MIT
Platform: UNKNOWN
Classifier: Development Status :: 4 - Beta
Classifier: Environment :: Console
Classifier: Intended Audience :: System Administrators
Classifier: License :: OSI Approved :: MIT License
Classifier: Operating System :: OS Independent
Classifier: Topic :: Software Development :: Libraries :: Python Modules
Classifier: Programming Language :: Python
Classifier: Programming Language :: Python :: 2.7
